AUTHORS
ChangeLog
LICENSE
README.rst
announce.rst
setup.cfg
setup.py
tox.ini
pdbcs/__init__.py
pdbcs/main.py
pdbcs.egg-info/PKG-INFO
pdbcs.egg-info/SOURCES.txt
pdbcs.egg-info/dependency_links.txt
pdbcs.egg-info/entry_points.txt
pdbcs.egg-info/not-zip-safe
pdbcs.egg-info/top_level.txt