Metadata-Version: 1.1
Name: pdbcs
Version: 0.3
Summary: pdb for setuptools console scripts
Home-page: https://github.com/dreamhost/pdbcs
Author: Doug Hellmann
Author-email: doug.hellmann@dreamhost.com
License: Apache-2
Keywords: setuptools
Platform: UNKNOWN
Classifier: Development Status :: 4 - Beta
Classifier: Environment :: Console
Classifier: Intended Audience :: Developers
Classifier: Intended Audience :: Information Technology
Classifier: License :: OSI Approved :: Apache Software License
Classifier: Operating System :: OS Independent
Classifier: Programming Language :: Python
